<?xml version="1.0" encoding="UTF-8"?>
<objects serializationModel="Studio.02.02.00">
	<object class="AudioFile" id="{32b6ad66-294a-4cbe-9f58-f57390cc3d29}">
		<property name="color">
			<value>Blue</value>
		</property>
		<property name="assetPath">
			<value>SFX/Player Weapons/24 Gauge Shotgun/24 Gauge Shotgun Reload Shells Bounce.mp3</value>
		</property>
		<property name="frequencyInKHz">
			<value>44.0999985</value>
		</property>
		<property name="channelCount">
			<value>1</value>
		</property>
		<property name="length">
			<value>10.109387755102041</value>
		</property>
		<relationship name="masterAssetFolder">
			<destination>{443236f2-2e67-4018-b62d-7081b70f8485}</destination>
		</relationship>
	</object>
</objects>
